src/__init__.py
src/__main__.py
src/auth_service.py
src/config.py
src/database.py
src/database_factory.py
src/database_interface.py
src/document_manager.py
src/embedding_service.py
src/http_config.py
src/http_server.py
src/intelligent_retrieval.py
src/models.py
src/postgres_database.py
src/server.py
src/sqlite_database.py
src/tinydb_database.py
src/auth/__init__.py
src/auth/client_authenticator.py
src/auth/client_registry.py
src/auth/discovery.py
src/auth/external_providers.py
src/auth/oauth21_provider.py
src/auth/pkce_verifier.py
src/auth/token_manager.py
src/auth/token_validator.py
src/config/__init__.py
src/config/http_config.py
src/config/local_config.py
src/security/__init__.py
src/security/audit_logger.py
src/security/middleware.py
src/security/validators.py
mcp_personal_assistant-0.2.2.dist-info/METADATA
mcp_personal_assistant-0.2.2.dist-info/WHEEL
mcp_personal_assistant-0.2.2.dist-info/entry_points.txt
mcp_personal_assistant-0.2.2.dist-info/licenses/LICENSE
mcp_personal_assistant-0.2.2.dist-info/RECORD
