Metadata-Version: 2.4
Name: mcp-personal-assistant
Version: 0.2.2
Summary: Personal Assistant MCP Server with SQLite/TinyDB support for status tracking, project management, todos, calendar functionality, and document storage
Project-URL: Homepage, https://github.com/swapnilsurdi/mcp-pa
Project-URL: Repository, https://github.com/swapnilsurdi/mcp-pa
Project-URL: Issues, https://github.com/swapnilsurdi/mcp-pa/issues
Project-URL: Documentation, https://github.com/swapnilsurdi/mcp-pa#readme
Author: MCP Personal Assistant Contributors
Maintainer: MCP Personal Assistant Contributors
License: MIT License
License-File: LICENSE
Keywords: calendar,claude,mcp,model-context-protocol,personal-assistant,productivity,project-management,sqlite,todo
Classifier: Development Status :: 4 - Beta
Classifier: Intended Audience :: Developers
Classifier: License :: OSI Approved :: MIT License
Classifier: Operating System :: OS Independent
Classifier: Programming Language :: Python :: 3
Classifier: Programming Language :: Python :: 3.10
Classifier: Programming Language :: Python :: 3.11
Classifier: Programming Language :: Python :: 3.12
Classifier: Topic :: Office/Business :: Scheduling
Classifier: Topic :: Software Development :: Libraries :: Python Modules
Classifier: Topic :: System :: System Shells
Requires-Python: >=3.10
Requires-Dist: cryptography>=41.0.0
Requires-Dist: mcp>=1.0.0
Requires-Dist: pydantic>=2.0.0
Requires-Dist: python-dateutil>=2.8.2
Requires-Dist: tinydb>=4.8.0
Provides-Extra: dev
Requires-Dist: black>=23.0.0; extra == 'dev'
Requires-Dist: flake8>=6.0.0; extra == 'dev'
Requires-Dist: isort>=5.12.0; extra == 'dev'
Requires-Dist: mypy>=1.0.0; extra == 'dev'
Requires-Dist: pytest-asyncio>=0.21.0; extra == 'dev'
Requires-Dist: pytest-cov>=4.0.0; extra == 'dev'
Requires-Dist: pytest>=7.0.0; extra == 'dev'
Provides-Extra: http
Requires-Dist: fastapi>=0.104.0; extra == 'http'
Requires-Dist: psycopg2-binary>=2.9.7; extra == 'http'
Requires-Dist: redis>=5.0.0; extra == 'http'
Requires-Dist: uvicorn>=0.24.0; extra == 'http'
